[
  {"model":"cursos.Curso", "fields":{
      "id": "1",
      "modulo": "Mayo - TT",
      "fInicio": "2019-05-07",
      "fFin": "2019-08-01",
      "estado": "Próximo",
      "cantClases": "26",
      "materiaID_id": "1",
      "profesorID_id": "3"
    }},
  {"model":"cursos.Curso", "fields":{
      "id": "2",
      "modulo": "C.C 1",
      "fInicio": "2019-05-13",
      "fFin": "2019-06-12",
      "estado": "Próximo",
      "cantClases": "10",
      "materiaID_id": "13",
      "profesorID_id": "12"
    }},
 {"model":"cursos.Curso", "fields":{
      "id": "3",
      "modulo": "cc3",
      "fInicio": "2019-05-06",
      "fFin": "2019-07-02",
      "estado": "En curso",
      "cantClases": "17",
      "materiaID_id": "2",
      "profesorID_id": "11"
    }}
]